migrations/0001_initial.py
migrations/0002_customuser_is_superuser.py
migrations/__init__.py
django_custom_user_auth-1.0.4.dist-info/METADATA
django_custom_user_auth-1.0.4.dist-info/WHEEL
django_custom_user_auth-1.0.4.dist-info/top_level.txt
django_custom_user_auth-1.0.4.dist-info/RECORD
