Metadata-Version: 2.1
Name: django-custom-user-auth
Version: 1.0.4
Requires-Dist: Django ==4.2.2
Requires-Dist: djangorestframework ==3.14.0
